PySimpleGUI/PySimpleGUI.py
PySimpleGUI/__init__.py
PySimpleGUI/__main__.py
pysimplegui-5.0.99.99.dist-info/LICENSE.txt
pysimplegui-5.0.99.99.dist-info/METADATA
pysimplegui-5.0.99.99.dist-info/WHEEL
pysimplegui-5.0.99.99.dist-info/entry_points.txt
pysimplegui-5.0.99.99.dist-info/top_level.txt
pysimplegui-5.0.99.99.dist-info/RECORD
