Metadata-Version: 2.2
Name: PySimpleGUI
Version: 5.0.99.99
Summary: PySimpleGUI is now located on a private PyPI server.  Please add to your pip command: -i https://PySimpleGUI.net/install
Author: PySimpleSoft Inc.
License: Proprietary
Project-URL: Homepage, https://www.PySimpleGUI.com
Keywords: GUI,UI,tkinter,Qt,WxPython,Remi,wrapper,simple,easy,beginner,novice,student,graphics
Classifier: Intended Audience :: Developers
Classifier: License :: Other/Proprietary License
Classifier: Operating System :: OS Independent
Classifier: Framework :: PySimpleGUI
Classifier: Framework :: PySimpleGUI :: 5
Classifier: Programming Language :: Python :: 3
Classifier: Programming Language :: Python :: 3.6
Classifier: Programming Language :: Python :: 3.7
Classifier: Programming Language :: Python :: 3.8
Classifier: Programming Language :: Python :: 3.9
Classifier: Programming Language :: Python :: 3.10
Classifier: Programming Language :: Python :: 3.11
Classifier: Programming Language :: Python :: 3.12
Classifier: Programming Language :: Python :: 3.13
Classifier: Programming Language :: Python :: 3.14
Classifier: Topic :: Multimedia :: Graphics
Requires-Python: >=3.6
License-File: LICENSE.txt
